voting_machine.v
module voting_machine #(
parameter idle =  2'b00,					// states and their corresponding numbers
parameter vote =  2'b01,
parameter hold =  2'b10,
parameter finish = 2'b11
)(
    input clk,							
    input rst,							// input High to reset counting  (active high)
    input i_candidate_1,				// input to vote for candidate 1
    input i_candidate_2,				// input to vote for candidate 2
    input i_candidate_3,				// input to vote for candidate 3
    input i_voting_over,				// input high to get total votes after voting is over

    output reg [31:0] o_count1,			// output for total number of votes of candidate 1
    output reg [31:0] o_count2,			// output for total number of votes of candidate 2
    output reg [31:0] o_count3			// output for total number of votes of candidate 3

);	  

reg [31:0] r_cand1_prev;					// store previous value of input for candidate 1
reg [31:0] r_cand2_prev;					// store previous value of input for candidate 2
reg [31:0] r_cand3_prev;					// store previous value of input for candidate 3

reg [31:0] r_counter_1;						// counting register for candidate 1
reg [31:0] r_counter_2;						// counting register for candidate 2
reg [31:0] r_counter_3;						// counting register for candidate 3

reg [1:0] r_present_state, r_next_state;		// present state and next state registers
//reg [1:0] r_state_no;					     // store state number
reg [3:0] r_hold_count;                        //counter for hold state

//////////// always block that assigns next state & internal reg operations /////////////////////////////////// 
always @(posedge clk or negedge rst)
	begin
		case (r_present_state)														

			idle: if (!rst)												// idle state operations
						begin
							r_next_state <= vote;									// assign next state vote when reset low
							//r_state_no <= 2'b01;
						end	

					else
						begin
						//r_present_state = idle;									// present state at the beginning
							r_counter_1 <= 32'b0;										// clear counting registers
							r_counter_2 <= 32'b0;
							r_counter_3 <= 32'b0;
							r_hold_count <= 4'b0000;

							r_next_state <= idle;									// assign next state as idle till reset not low
							//r_state_no <= 2'b0;
						end
				

			vote: if (i_voting_over == 1'b1)									// check if voting is over
						begin
							r_next_state <= finish;								// if over is high go to finish state
							//r_state_no <= 2'b11;
						end
												// if over is low contiue counting
					else if (i_candidate_1 == 1'b0 && r_cand1_prev == 1'b1)         // check falling edge of input candidate1 so only single input is regeistered 
						begin
							r_counter_1 <= r_counter_1 + 1'b1;								// increment counter for candidate 1
							//r_counter_2 <= r_counter_2;									// keep previous value of counter 
							//r_counter_3 <= r_counter_3;									// keep previous value of counter

							r_next_state <= hold;									// got to hold state
							//r_state_no <= 2'b10;
						end

					else if (i_candidate_2 == 1'b0 && r_cand2_prev == 1'b1) 		// check falling edge of input candidate2 so only single input is regeistered
						begin
							//r_counter_1 <= r_counter_1;									// keep previous value of counter 
							r_counter_2 <= r_counter_2 + 1'b1;								// increment counter for candidate 2
							//r_counter_3 <= r_counter_3;									// keep previous value of counter 

							r_next_state <= hold;									// got to hold state
							//r_state_no <= 2'b10;
						end

					else if (i_candidate_3 == 1'b0 && r_cand3_prev == 1'b1) 		// check falling edge of input candidate3 so only single input is regeistered
						begin
							//r_counter_1 <= r_counter_1;									// keep previous value of counter
							//r_counter_2 <= r_counter_2;									// keep previous value of counter
							r_counter_3 <= r_counter_3 + 1'b1;								// increment counter for candidate 3

							r_next_state <= hold;									// got to hold state
							//r_state_no <= 2'b10;
						end
					else															// none of the input present or more than 1 input present at same time
						begin
							r_counter_1 <= r_counter_1;									// keep previous value of counter
							r_counter_2 <= r_counter_2;									
							r_counter_3 <= r_counter_3;

							r_next_state <= vote;
							//r_state_no <= 2'b01;
						end

			hold: if (i_voting_over == 1'b1)									// check if over input is high
						begin
							r_next_state <= finish;									// go to finish state
							//r_state_no <= 2'b11;
						end

					else 
						begin
							if (r_hold_count != 4'b1111) begin
								r_hold_count = r_hold_count + 1'b1;
							end
							else begin
							    r_next_state <= vote;									// if over is low go to vote state
							end
							//r_state_no <= 2'b01;
						end

			finish: if (i_voting_over == 1'b0)										
						begin
							r_next_state <= idle;									// if over is low go to idle state
							//r_state_no <= 2'b0;
						end

					else
						begin
							r_next_state <= finish;									// remain in finish state if over is high
							//r_state_no <= 2'b11;
						end

			default: 
				begin 
					r_counter_1 <= 32'b0;											// default values for resgisters
					r_counter_2 <= 32'b0;
					r_counter_3 <= 32'b0;
					r_hold_count <= 4'b0000;

					r_next_state <= idle;										// by default go to idle state at the begining
					//r_state_no <= 2'b0;
				end
		endcase
	end	  

////////////// always block that performs assignment of regsiters and output on clock signal //////////////////////////////
always @(posedge clk or negedge rst)													// work on positive edge of clock 
	begin				

      if (rst == 1'b1)
			begin
				 r_present_state <= idle;											// remain in idle state when reset is high
													
				 o_count1 <= 32'b0; 												// reset final output count  
				 o_count2 <= 32'b0;
				 o_count3 <= 32'b0;
				 r_hold_count <= 4'b0000;
			end 
			
		else if (rst == 1'b0 && i_voting_over == 1'b1)											// if voting process is i.e.over is high
			begin
				 o_count1 <= r_counter_1; 											// provide value of counting registers at output
				 o_count2 <= r_counter_2;
				 o_count3 <= r_counter_3;
			end
		
		else
			begin
				r_present_state <= r_next_state;									// if reset is low keep assigning next state to present state
				r_cand1_prev <= i_candidate_1;									// keep assigning input of candidate 1 to internal register
				r_cand2_prev <= i_candidate_2;
				r_cand3_prev <= i_candidate_3;
			end
	
	end	

endmodule

voting_tb.v
`timescale 1ns / 1ps

module voting_tb;

    reg clk;
    reg rst;
    reg i_candidate_1;
    reg i_candidate_2;
    reg i_candidate_3;
    reg i_voting_over;

    wire [31:0] o_count1;
    wire [31:0] o_count2;
    wire [31:0] o_count3;

    // Instantiate the voting machine
    voting_machine uut (
        .clk(clk),
        .rst(rst),
        .i_candidate_1(i_candidate_1),
        .i_candidate_2(i_candidate_2),
        .i_candidate_3(i_candidate_3),
        .i_voting_over(i_voting_over),
        .o_count1(o_count1),
        .o_count2(o_count2),
        .o_count3(o_count3)
    );

    // Generate clock
    always #5 clk = ~clk;

    initial begin
        $dumpfile("voting.vcd");
        $dumpvars(0, voting_tb);

        clk = 0;
        rst = 1;
        i_candidate_1 = 1;
        i_candidate_2 = 1;
        i_candidate_3 = 1;
        i_voting_over = 0;

        #10 rst = 0;

        // Simulate a vote for candidate 1
        #10 i_candidate_1 = 0;
        #10 i_candidate_1 = 1;

        // Simulate a vote for candidate 2
        #20 i_candidate_2 = 0;
        #10 i_candidate_2 = 1;

        // Simulate a vote for candidate 3
        #20 i_candidate_3 = 0;
        #10 i_candidate_3 = 1;

        // Finish voting
        #50 i_voting_over = 1;

        #20 i_voting_over = 0;

        #20 $display("Vote counts - C1: %d, C2: %d, C3: %d", o_count1, o_count2, o_count3);
        #10 $finish;
    end
endmodule

voting.vcd
$date
	Fri May 02 00:53:49 2025
$end
$version
	Icarus Verilog
$end
$timescale
	1ps
$end
$scope module voting_tb $end
$var wire 32 ! o_count3 [31:0] $end
$var wire 32 " o_count2 [31:0] $end
$var wire 32 # o_count1 [31:0] $end
$var reg 1 $ clk $end
$var reg 1 % i_candidate_1 $end
$var reg 1 & i_candidate_2 $end
$var reg 1 ' i_candidate_3 $end
$var reg 1 ( i_voting_over $end
$var reg 1 ) rst $end
$scope module uut $end
$var wire 1 $ clk $end
$var wire 1 % i_candidate_1 $end
$var wire 1 & i_candidate_2 $end
$var wire 1 ' i_candidate_3 $end
$var wire 1 ( i_voting_over $end
$var wire 1 ) rst $end
$var parameter 2 * finish $end
$var parameter 2 + hold $end
$var parameter 2 , idle $end
$var parameter 2 - vote $end
$var reg 32 . o_count1 [31:0] $end
$var reg 32 / o_count2 [31:0] $end
$var reg 32 0 o_count3 [31:0] $end
$var reg 32 1 r_cand1_prev [31:0] $end
$var reg 32 2 r_cand2_prev [31:0] $end
$var reg 32 3 r_cand3_prev [31:0] $end
$var reg 32 4 r_counter_1 [31:0] $end
$var reg 32 5 r_counter_2 [31:0] $end
$var reg 32 6 r_counter_3 [31:0] $end
$var reg 4 7 r_hold_count [3:0] $end
$var reg 2 8 r_next_state [1:0] $end
$var reg 2 9 r_present_state [1:0] $end
$upscope $end
$upscope $end
$enddefinitions $end
$comment Show the parameter values. $end
$dumpall
b1 -
b0 ,
b10 +
b11 *
$end
#0
$dumpvars
bx 9
bx 8
bx 7
bx 6
bx 5
bx 4
bx 3
bx 2
bx 1
bx 0
bx /
bx .
1)
0(
1'
1&
1%
0$
bx #
bx "
bx !
$end
#5000
b0 8
b0 6
b0 5
b0 4
b0 7
b0 !
b0 0
b0 "
b0 /
b0 #
b0 .
b0 9
1$
#10000
b1 3
b1 2
b1 1
b1 8
0$
0)
#15000
b1 9
1$
#20000
0$
0%
#25000
b0 1
b10 8
b1 4
1$
#30000
0$
1%
#35000
b1 8
b1 1
b10 9
1$
#40000
0$
#45000
b1 9
b1 7
1$
#50000
0$
0&
#55000
b10 8
b1 5
b0 2
1$
#60000
0$
1&
#65000
b1 2
b10 9
b1 8
1$
#70000
0$
#75000
b1 9
b10 7
1$
#80000
0$
0'
#85000
b0 3
b10 8
b1 6
1$
#90000
0$
1'
#95000
b1 8
b1 3
b10 9
1$
#100000
0$
#105000
b1 9
b11 7
1$
#110000
0$
#115000
1$
#120000
0$
#125000
1$
#130000
0$
#135000
1$
#140000
0$
1(
#145000
b1 !
b1 0
b1 "
b1 /
b1 #
b1 .
b11 8
1$
#150000
0$
#155000
1$
#160000
0$
0(
#165000
b11 9
b1 8
1$
#170000
0$
#175000
b0 8
b1 9
1$
#180000
0$
#185000
b0 9
b1 8
1$
